postcodewizard/__init__.py
postcodewizard/client.py
postcodewizard-1.0.1.dist-info/METADATA
postcodewizard-1.0.1.dist-info/WHEEL
postcodewizard-1.0.1.dist-info/RECORD
