Metadata-Version: 2.4
Name: postcodewizard
Version: 1.0.1
Summary: The official PostcodeWizard python package
Project-URL: Homepage, https://postcodewizard.nl
Project-URL: Documentation, https://api.postcodewizard.nl/docs/api
Author-email: FlowEngine <info@flowengine.nl>
License-Expression: MIT
Classifier: Operating System :: OS Independent
Classifier: Programming Language :: Python :: 3
Requires-Python: >=3.9.6
Provides-Extra: dev
Requires-Dist: pytest; extra == 'dev'
